networkqa/__init__.py
networkqa/networkqa.py
tests/__init__.py
tests/test_networkqa.py
networkqa-0.0.18.dist-info/LICENSE.txt
networkqa-0.0.18.dist-info/METADATA
networkqa-0.0.18.dist-info/WHEEL
networkqa-0.0.18.dist-info/top_level.txt
networkqa-0.0.18.dist-info/RECORD
