Metadata-Version: 2.1
Name: networkqa
Version: 0.0.18
Summary: A module to aid in automated qa of networking devices
Home-page: http://naic-gitlab.wwt.com/lalonder/networkqa
Author: Richard Lalonde
Author-email: richard.lalonde@wwt.com
License: UNKNOWN
Platform: UNKNOWN
Classifier: Development Status :: 3 - Alpha
Classifier: Programming Language :: Python :: 3
Classifier: License :: OSI Approved :: GNU General Public License v3 (GPLv3)
Classifier: Operating System :: OS Independent
Requires-Python: >=3.6
Requires-Dist: openpyxl
